{
  "last_heartbeat": "2026-05-31T18:46:52.501Z",
  "engine_status": "running",
  "execution_log": [
    {
      "task_id": "project-suggestions",
      "status": "success",
      "timestamp": "2026-05-31T16:48:34.065Z",
      "duration_ms": 57456
    },
    {
      "task_id": "project-suggestions",
      "status": "success",
      "timestamp": "2026-05-31T16:49:43.357Z",
      "duration_ms": 69289
    },
    {
      "task_id": "anatomy-rescan",
      "status": "success",
      "timestamp": "2026-05-31T21:00:01.007Z",
      "duration_ms": 501
    }
  ],
  "dead_letter_queue": [],
  "upcoming": []
}